.gitignore
LICENSE
README.md
setup.py
qz7.subprocess_w.egg-info/PKG-INFO
qz7.subprocess_w.egg-info/SOURCES.txt
qz7.subprocess_w.egg-info/dependency_links.txt
qz7.subprocess_w.egg-info/top_level.txt
qz7/subprocess_w/__init__.py