Metadata-Version: 2.1
Name: qz7.subprocess-w
Version: 0.0.1
Summary: A Popen wrapper for graceful process termination
Home-page: http://github.com/parantapa/qz7.subprocess_w
Author: Parantapa Bhattacharya
Author-email: pb+pypi@parantapa.net
License: UNKNOWN
Platform: UNKNOWN
Classifier: Programming Language :: Python :: 3
Classifier: License :: OSI Approved :: MIT License
Classifier: Operating System :: OS Independent
